addcomb.cpython-39-darwin.so
addcomb-0.2.5.dist-info/LICENSE
addcomb-0.2.5.dist-info/METADATA
addcomb-0.2.5.dist-info/WHEEL
addcomb-0.2.5.dist-info/top_level.txt
addcomb-0.2.5.dist-info/RECORD
