Metadata-Version: 2.1
Name: addcomb
Version: 0.2.5
Summary: Fast Additive Combinatorics for use in Sage
Home-page: UNKNOWN
Author: Matt Torrence <gh-Torrencem>
Author-email: UNKNOWN
License: UNKNOWN
Platform: UNKNOWN
